fastosc/__init__.py
fastosc/py.typed
fastosc/dispatcher/__init__.py
fastosc/dispatcher/handler.py
fastosc/docs/__init__.py
fastosc/message/__init__.py
fastosc/message/arg_value.py
fastosc/message/convert.py
fastosc/message/osc_bundle.py
fastosc/message/osc_bundle_builder.py
fastosc/message/osc_message.py
fastosc/message/osc_message_builder.py
fastosc/message/parsing/__init__.py
fastosc/message/parsing/ntp.py
fastosc/message/parsing/osc_types.py
fastosc/router/__init__.py
fastosc/server/__init__.py
fastosc/server/dispatcher_server.py
fastosc/server/server_base.py
fastosc/server/udp/udp_pull_server.py
fastosc/server/udp/udp_server_base.py
fastosc-0.0.7.dist-info/METADATA
fastosc-0.0.7.dist-info/WHEEL
fastosc-0.0.7.dist-info/top_level.txt
fastosc-0.0.7.dist-info/RECORD
